triarc/__init__.py
triarc/backend.py
triarc/bot.py
triarc/errors.py
triarc/mutator.py
triarc/backends/__init__.py
triarc/backends/discord.py
triarc/backends/irc.py
triarc/mutators/__init__.py
triarc/mutators/antihilite.py
triarc-0.2.2.dist-info/LICENSE
triarc-0.2.2.dist-info/METADATA
triarc-0.2.2.dist-info/WHEEL
triarc-0.2.2.dist-info/top_level.txt
triarc-0.2.2.dist-info/RECORD
