Metadata-Version: 2.1
Name: triarc
Version: 0.2.2
Summary: A trio library for automating responses to commands (bots) and the like. Ships with an IRC backend.
Home-page: UNKNOWN
Author: Gustavo Ramos Rehermann
Author-email: rehermann6046@gmail.com
License: COIL
Keywords: bot network async trio irc
Platform: UNKNOWN
Classifier: Framework :: Trio
Classifier: Topic :: System :: Networking
Classifier: Topic :: Software Development :: Libraries
Classifier: Topic :: Software Development :: Libraries :: Application Frameworks
Classifier: Topic :: Communications
